confflow/__init__.py
confflow/config/__init__.py
confflow/config/config.py
confflow/config/entry.py
confflow/config_factory.py
confflow/constraints/__init__.py
confflow/constraints/constraint.py
confflow/constraints/list.py
confflow/constraints/numeric.py
confflow/constraints/string.py
confflow/fields/__init__.py
confflow/fields/communication.py
confflow/fields/network.py
confflow/formatter.py
confflow/manager/__init__.py
confflow/manager/confflow.py
confflow/manager/group.py
confflow/manager/manager.py
confflow/mixins.py
confflow/schema/__init__.py
confflow/schema/field.py
confflow/schema/schema.py
confflow/types.py
confflow-3.1.1.dist-info/LICENSE
confflow-3.1.1.dist-info/METADATA
confflow-3.1.1.dist-info/WHEEL
confflow-3.1.1.dist-info/RECORD
