Metadata-Version: 2.1
Name: confflow
Version: 3.1.1
Summary: A configuration manager for Python projects
Home-page: https://www.linkedin.com/in/pedro-jose-mora-gallegos
License: MIT
Author: Pedro José Mora Gallegos
Author-email: pedrojosemoragallegos@outlook.de
Requires-Python: >=3.10,<3.14
Classifier: License :: OSI Approved :: MIT License
Classifier: Programming Language :: Python :: 3
Classifier: Programming Language :: Python :: 3.10
Classifier: Programming Language :: Python :: 3.11
Classifier: Programming Language :: Python :: 3.12
Classifier: Programming Language :: Python :: 3.13
Project-URL: Repository, https://github.com/pedrojosemoragallegos/confflow
